{
  "dogs": [
    {
      "id": 1,
      "nome": "Bolt",
      "idade": 2,
      "peso": 8,
      "raca": "Poodle Toy",
      "porte": "Pequeno",
      "foto": "https://fly.metroimg.com/upload/q_85,w_700/https://uploads.metroimg.com/wp-content/uploads/2020/02/26145040/poodle1.jpg",
      "foto2": "https://blog.cobasi.com.br/wp-content/uploads/2021/05/micro-poodle-toy-1.jpg",
      "foto3": "https://tudodebicho.vtexassets.com/arquivos/cachorro-shih-poo-maltipoo-bege-fofo-andando-em-um-deck-de-madeira.jpg",
      "bio": "Bolt é um cachorrinho cheio de energia e muito brincalhão. Ele adora correr e explorar novos lugares, sempre espalhando alegria por onde passa.",
      "abrigo": "Lar dos Peludos"
    },
    {
      "id": 2,
      "nome": "Luna",
      "idade": 3,
      "peso": 7,
      "raca": "Shih Tzu",
      "porte": "Pequeno",
      "foto": "https://encrypted-tbn1.gstatic.com/images?q=tbn:ANd9GcQtXiYXNNXWrBNnAZP5uZ-YHIAhOobtGCVWVw8MPaH8nIVWsk7FRNe3tg0WSmYRvMp-Gg9rMdMu16X0bqw0g_8Tqg",
      "foto2": "https://petanjo.com/blog/wp-content/uploads/2023/05/shih-tzu-15.jpg",
      "foto3": "https://p2.trrsf.com/image/fget/cf/1200/900/middle/images.terra.com/2024/07/03/79816500-shih-tzu.jpg",
      "bio": "Luna é uma cachorrinha muito esperta e afetuosa. Foi resgatada das ruas e agora está pronta para encontrar um lar amoroso onde possa receber todo o carinho que merece.",
      "abrigo": "Patinhas Felizes"
    },
    {
      "id": 3,
      "nome": "Max",
      "idade": 1,
      "peso": 6,
      "raca": "Chihuahua",
      "porte": "Pequeno",
      "foto": "https://i0.statig.com.br/bancodeimagens/er/g7/7p/erg77pxjsqiwg7doduefmama5.jpg",
      "foto2": "https://petcare.com.br/wp-content/uploads/2022/11/81.jpg",
      "foto3": "https://upload.wikimedia.org/wikipedia/commons/2/24/Babylone_3ans1.jpg",
      "bio": "Max é um pequeno aventureiro com um grande coração. Sempre curioso e cheio de energia, ele adora brincar e receber carinho.",
      "abrigo": "Amigos de Quatro Patas"
    },
    {
      "id": 4,
      "nome": "Bella",
      "idade": 4,
      "peso": 9,
      "raca": "Dachshund",
      "porte": "Pequeno",
      "foto": "https://www.patasdacasa.com.br/sites/default/files/styles/article_detail_1200/public/noticias/2021/02/alopecia-canina-saiba-mais-sobre-a-queda-de-pelos-em-dachshunds.jpg.webp?itok=QEWOZop5",
      "foto2": "https://filhotesdaserra.com.br/wp-content/uploads/2021/08/dachshund-1519374_1280-1200x700.jpg",
      "foto3": "https://www.doglife.com.br/blog/assets/post/dachshund-saiba-tudo-sobre-essa-raca-660af6a8f81cb54ff7978c43/dachshund.jpg?w=480",
      "bio": "Bella é uma cachorrinha dócil e carinhosa. Com seu jeitinho encantador, conquista a todos ao seu redor.",
      "abrigo": "Coração Canino"
    },
    {
      "id": 5,
      "nome": "Charlie",
      "idade": 2,
      "peso": 10,
      "raca": "Yorkshire Terrier",
      "porte": "Pequeno",
      "foto": "https://encrypted-tbn2.gstatic.com/images?q=tbn:ANd9GcR0gLoxezclGoSSKOkCT7hkwlx8bm2_-UlpAIagCMEObOgu-xw-_wy6CYLSz-HVxnOCleBUGuO1FildXSvoaqBxnw",
      "foto2": "https://jpimg.com.br/uploads/2023/07/yorkshire-terrier-tudo-o-que-voce-precisa-saber-sobre-essa-raca.jpg",
      "foto3": "https://encrypted-tbn0.gstatic.com/images?q=tbn:ANd9GcQVD4jlbK__phw9OJcZHTCw4PmeK8hgAfCM2Q&s",
      "bio": "Charlie é um cãozinho leal e brincalhão. Sempre pronto para um novo desafio, ele ama estar perto de sua família.",
      "abrigo": "Casa dos Aumigos"
    },
    {
      "id": 6,
      "nome": "Rocky",
      "idade": 3,
      "peso": 12,
      "raca": "Beagle",
      "porte": "Médio",
      "foto": "https://www.zooplus.pt/magazine/wp-content/uploads/2018/06/beagle_2.jpg",
      "foto2": "https://encrypted-tbn0.gstatic.com/images?q=tbn:ANd9GcQHWRM0xlowOQioBQy1zVHFQ1EaNvKOelZMig&s",
      "foto3": "https://blog-static.petlove.com.br/wp-content/uploads/2018/05/beagle-filhote.jpg",
      "bio": "Rocky é um Beagle cheio de energia e com um faro incrível para aventuras. Alegre e sociável, ele adora interagir com outros cães.",
      "abrigo": "Adote um Focinho"
    },
    {
      "id": 7,
      "nome": "Duke",
      "idade": 5,
      "peso": 15,
      "raca": "Cocker Spaniel",
      "porte": "Médio",
      "foto": "https://blog-static.petlove.com.br/wp-content/uploads/2019/12/cocker_ingles.jpg",
      "foto2": "https://cobasi.vteximg.com.br/arquivos/ids/622425/cocker-spaniel-english.png?v=637571426914900000",
      "foto3": "https://box4pets.com.br/cdn/shop/articles/cocker-spaniel_1920x.jpg?v=1655305854",
      "bio": "Duke é um Cocker Spaniel muito amigável e dócil. Seu olhar expressivo e carisma fazem dele um grande companheiro.",
      "abrigo": "Refúgio dos Focinhos"
    },
    {
      "id": 8,
      "nome": "Maggie",
      "idade": 2,
      "peso": 16,
      "raca": "Border Collie",
      "porte": "Médio",
      "foto": "https://www.dogvibe.com.br/wp-content/uploads/2023/05/guia_racas_border_collie.webp",
      "foto2": "https://www.racoesreis.com.br/wordpress/wp-content/uploads/cachorro-origem5.jpg",
      "foto3": "https://www.infoescola.com/wp-content/uploads/2010/08/border-collie_593634296.jpg",
      "bio": "Maggie é uma Border Collie inteligente e ativa. Sempre pronta para aprender novos truques, ela adora desafios e brincadeiras.",
      "abrigo": "Coração Canino"
    },
    {
      "id": 9,
      "nome": "Toby",
      "idade": 4,
      "peso": 18,
      "raca": "Bulldog Francês",
      "porte": "Médio",
      "foto": "https://p2.trrsf.com/image/fget/cf/940/0/images.terra.com/2024/06/28/651347317-buldogue-frances.jpg",
      "foto2": "https://bulldogbazar.com/wp-content/uploads/2024/06/bulldog-frances-preto-800x800.png",
      "foto3": "https://www.zooplus.pt/magazine/wp-content/uploads/2020/12/BF_1.jpg",
      "bio": "Toby é um Bulldog Francês encantador, que ama receber carinho e estar no colo de quem gosta.",
      "abrigo": "Peludos & Cia"
    },
    {
      "id": 10,
      "nome": "Lucy",
      "idade": 3,
      "peso": 14,
      "raca": "Pastor Australiano",
      "porte": "Médio",
      "foto": "https://www.cobasi.com.br/arquivos/pastor-australiano-meio.png?v=637613614003970000",
      "foto2": "https://upload.wikimedia.org/wikipedia/commons/c/c2/Australianshepherd01.jpg",
      "foto3": "https://guiapetfriendly.com.br/wp-content/uploads/2024/03/pastor-australiano.jpeg",
      "bio": "Lucy é uma Pastor Australiano cheia de energia e lealdade. Sempre pronta para aventuras, adora correr e brincar ao ar livre.",
      "abrigo": "Patinhas Felizes"
    },
    {
      "id": 11,
      "nome": "Zeus",
      "idade": 6,
      "peso": 30,
      "raca": "Golden Retriever",
      "porte": "Grande",
      "foto": "https://static.wixstatic.com/media/db516d_a7f7619f878f4c29948251d50d7f8de9~mv2.jpg/v1/fill/w_569,h_512,al_c,lg_1,q_80,usm_1.20_1.00_0.01,enc_avif,quality_auto/db516d_a7f7619f878f4c29948251d50d7f8de9~mv2.jpg",
      "foto2": "https://encrypted-tbn0.gstatic.com/images?q=tbn:ANd9GcRqS1EFHNViXoZoK1xe5WS29QZgOjcdJXc9fQ&s",
      "foto3": "https://encrypted-tbn0.gstatic.com/images?q=tbn:ANd9GcT7q_UUiSmBSUgmrF7VP2keAyPZNpG8b0uW3hGqDHqlg4CwrMXxVQXPusCMdbevuO78FIs&usqp=CAU",
      "bio": "Zeus é um Golden Retriever dócil e brincalhão. Ele ama interagir com pessoas e sempre está pronto para distribuir amor e alegria.",
      "abrigo": "Patinhas Felizes"
    },
    {
      "id": 12,
      "nome": "Rex",
      "idade": 4,
      "peso": 40,
      "raca": "Rottweiler",
      "porte": "Grande",
      "foto": "https://www.animalepetshop.com.br/wp-content/uploads/2016/03/rotweiller-1.jpg",
      "foto2": "https://encrypted-tbn0.gstatic.com/images?q=tbn:ANd9GcQ7D00cghxGVPsZrh0UEJmKPBs5PXG-N4K2rQ&s",
      "foto3": "https://tudosobrecachorros.com.br/wp-content/uploads/rottweiler-na-grama-e1336965114346.jpg",
      "bio": "Rex é um Rottweiler imponente e protetor, mas ao mesmo tempo muito amoroso com sua família. Leal e corajoso, ele é um verdadeiro guardião.",
      "abrigo": "Casa dos Aumigos"
    },
    {
      "id": 13,
      "nome": "Thor",
      "idade": 5,
      "peso": 35,
      "raca": "Husky Siberiano",
      "porte": "Grande",
      "foto": "https://st2.depositphotos.com/1007517/49567/i/450/depositphotos_495673738-stock-photo-siberian-husky-puppy-outdoors.jpg",
      "foto2": "https://encrypted-tbn0.gstatic.com/images?q=tbn:ANd9GcTSImL49olub_M6AHluQp5g1s_x5_aKV0Mo8Q&s",
      "foto3": "https://i0.wp.com/luludapomerania.net/wp-content/uploads/2024/02/1-36-1.jpg?resize=770%2C770&ssl=1",
      "bio": "Thor é um Husky Siberiano cheio de energia e personalidade. Ele ama correr e explorar, sempre demonstrando seu espírito livre.",
      "abrigo": "Refúgio dos Focinhos"
    },
    {
      "id": 14,
      "nome": "Athena",
      "idade": 3,
      "peso": 32,
      "raca": "Labrador Retriever",
      "porte": "Grande",
      "foto": "https://upload.wikimedia.org/wikipedia/commons/3/34/Labrador_on_Quantock_%282175262184%29.jpg",
      "foto2": "https://encrypted-tbn0.gstatic.com/images?q=tbn:ANd9GcRLmbQyZocGoQisUxyjT3nnmERslAwVZmRnRg&s",
      "foto3": "https://encrypted-tbn0.gstatic.com/images?q=tbn:ANd9GcT9Esvj34eXBo2sRyedqMta57_CsLwgDxWX8A&s",
      "bio": "Athena é uma Labrador Retriever carinhosa e brincalhona. Sempre cheia de energia, ela adora nadar e se divertir ao ar livre.",
      "abrigo": "Esperança Animal"
    },
    {
      "id": 15,
      "nome": "Gaia",
      "idade": 2,
      "peso": 38,
      "raca": "Pastor Alemão",
      "porte": "Grande",
      "foto": "https://premierpet.com.br/wp-content/uploads/2024/03/pastor-alemao-filhote-1024x683.jpg",
      "foto2": "https://cobasi.vteximg.com.br/arquivos/ids/728382/pastor-alemao-filhote.png?v=637593663339670000",
      "foto3": "https://encrypted-tbn0.gstatic.com/images?q=tbn:ANd9GcQfi0yBI4DMbBbVM4_EDwWumZcOu_GNb7kXcQ&s",
      "bio": "Gaia é uma Pastor Alemão muito inteligente e protetora. Com seu instinto leal, ela está sempre pronta para cuidar de quem ama.",
      "abrigo": "Esperança Animal"
    },
    {
      "id": 16,
      "nome": "Apollo",
      "idade": 4,
      "peso": 28,
      "raca": "Doberman",
      "porte": "Grande",
      "foto": "https://media.istockphoto.com/id/1223511966/pt/foto/beautiful-tan-and-black-german-pinscher.jpg?s=612x612&w=0&k=20&c=xgD18qRLARmqtpVVAZPkw_5J5SsO9MmmboxscLDuZyE=",
      "foto2": "https://www.infoescola.com/wp-content/uploads/2010/08/doberman_223996249.jpg",
      "foto3": "https://cobasi.vteximg.com.br/arquivos/ids/264314/Doberman.jpg?v=637020902834530000",
      "bio": "Apollo é um Doberman forte e destemido, mas também muito apegado a quem confia. Com ele, qualquer um se sente seguro e amado.",
      "abrigo": "Amigos de Quatro Patas"
    },
    {
      "id": 17,
      "nome": "Lola",
      "idade": 3,
      "peso": 6,
      "raca": "Pug",
      "porte": "Pequeno",
      "foto": "https://midias.agazeta.com.br/2024/03/26/desafios-e-controversias-proibir-ou-nao-a-criacao-de-shih-tzu-pug-e-buldogue-2054955-article.jpg",
      "foto2": "https://c.files.bbci.co.uk/41A0/production/_124800861_gettyimages-469360172.jpg",
      "foto3": "https://cobasi.vteximg.com.br/arquivos/ids/372656/pug-filhote.png?v=637414023654100000",
      "bio": "Lola é uma Pug carinhosa e cheia de charme. Adora um colo e sempre busca atenção com seu jeitinho doce.",
      "abrigo": "Amigos de Quatro Patas"
    },
    {
      "id": 18,
      "nome": "Simba",
      "idade": 5,
      "peso": 9,
      "raca": "Spitz Alemão",
      "porte": "Pequeno",
      "foto": "https://www.equilibrio-petfood.com/wp-content/uploads/2023/02/image-344.png",
      "foto2": "https://www.patasdacasa.com.br/sites/default/files/2024-07/spitz-alemao-capa.jpg",
      "foto3": "https://encrypted-tbn0.gstatic.com/images?q=tbn:ANd9GcSV5ypw3_6XkrYE8Q_UNkTPsSboMoOFOXeXDw&s",
      "bio": "Simba é um Spitz Alemão encantador e cheio de energia. Ele adora brincar e está sempre pronto para se divertir.",
      "abrigo": "Santuário dos Cães"
    },
    {
      "id": 19,
      "nome": "Diana",
      "idade": 2,
      "peso": 10,
      "raca": "Cavalier King Charles Spaniel",
      "porte": "Pequeno",
      "foto": "https://www.azpetshop.com.br/img/news/89/000.webp",
      "foto2": "https://upload.wikimedia.org/wikipedia/commons/5/5f/CarterBIS.Tiki.13.6.09.jpg",
      "foto3": "https://box4pets.com.br/cdn/shop/articles/cavalier-king-charles-spaniel-meio_1920x.png?v=1650892773",
      "bio": "Diana é uma Cavalier King Charles Spaniel doce e meiga. Seu olhar cativante conquista qualquer pessoa.",
      "abrigo": "Santuário dos Cães"
    },
    {
      "id": 20,
      "nome": "Zion",
      "idade": 4,
      "peso": 13,
      "raca": "Schnauzer",
      "porte": "Médio",
      "foto": "https://www.azpetshop.com.br/img/news/88/000.webp",
      "foto2": "https://fly.metroimg.com/upload/q_85,w_700/https://uploads.metroimg.com/wp-content/uploads/2020/02/19165610/aadad.jpg",
      "foto3": "https://p2.trrsf.com/image/fget/cf/1200/1200/middle/images.terra.com/2024/04/02/577382103-schnauzer.jpg",
      "bio": "Zion é um Schnauzer cheio de estilo e atitude. Sempre atento, ele é um grande companheiro para qualquer momento.",
      "abrigo": "Adote um Focinho"
    },
    {
      "id": 21,
      "nome": "Maya",
      "idade": 3,
      "peso": 11,
      "raca": "Basenji",
      "porte": "Médio",
      "foto": "https://www.petz.com.br/cachorro/racas/basenji/img/basenji-caracteristicas-guia-racas.webp",
      "foto2": "https://encrypted-tbn0.gstatic.com/images?q=tbn:ANd9GcQcCDcm07Wbr7GUMv_fiwuNdcWqcgwqcuahSw&s",
      "foto3": "https://www.purina.pt/sites/default/files/2021-02/BREED%20Hero_0006_basenji_0.jpg",
      "bio": "Maya é uma Basenji esperta e independente. Com sua personalidade única, encanta a todos que a conhecem.",
      "abrigo": "Adote um Focinho"
    },
    {
      "id": 22,
      "nome": "Fred",
      "idade": 6,
      "peso": 16,
      "raca": "Whippet",
      "porte": "Médio",
      "foto": "https://blog.polipet.com.br/wp-content/uploads/2023/11/AdobeStock_171997457-scaled.jpeg",
      "foto2": "https://encrypted-tbn0.gstatic.com/images?q=tbn:ANd9GcSKLz-FruAWUT9f6OQ1M8Sw8DVZdzYcnJLCow&s",
      "foto3": "https://i.pinimg.com/736x/b8/ca/ff/b8caff6ad6c3559bf4c23d45a3c4b9ec.jpg",
      "bio": "Fred é um Whippet ágil e carinhoso. Com um coração enorme, ele adora correr e receber carinho.",
      "abrigo": "Adote um Focinho"
    },
    {
      "id": 23,
      "nome": "Penny",
      "idade": 5,
      "peso": 18,
      "raca": "Samoyeda",
      "porte": "Grande",
      "foto": "https://uploads.metroimg.com/wp-content/uploads/2020/06/10125757/harold-dixon-ljwfTpPLySk-unsplash.jpg",
      "foto2": "https://encrypted-tbn0.gstatic.com/images?q=tbn:ANd9GcSbOjL9vyRVvJ0ApElbSd5pcJT0LOvSKpSLzQ&s",
      "foto3": "https://blog-static.petlove.com.br/wp-content/uploads/2018/05/samoieda-adulto-sala.jpg",
      "bio": "Penny é uma Samoyeda fofíssima e cheia de energia. Sua pelagem macia e seu sorriso encantador fazem dela uma companheira perfeita.",
      "abrigo": "Coração Canino"
    },
    {
      "id": 24,
      "nome": "Hulk",
      "idade": 4,
      "peso": 35,
      "raca": "Bernese Mountain Dog",
      "porte": "Grande",
      "foto": "https://www.rover.com/blog/wp-content/uploads/2019/06/bernese-mountain-dog-1024x680.jpg",
      "foto2": "https://www.patasdacasa.com.br/sites/default/files/styles/article_detail_1200/public/2024-04/bernese-filhote.jpg.webp?itok=8DPCkgQd",
      "foto3": "https://www.portofilhote.com.br/wp-content/uploads/2017/08/FB_IMG_1501290349202.jpg",
      "bio": "Hulk é um Bernese Mountain Dog grandão e carinhoso. Adora estar perto das pessoas e espalhar alegria por onde passa.",
      "abrigo": ""
    },
    {
      "id": 25,
      "nome": "Daisy",
      "idade": 2,
      "peso": 6,
      "raca": "Maltês",
      "porte": "Pequeno",
      "foto": "https://www.petz.com.br/blog/wp-content/uploads/2023/04/como-cuidar-de-um-cachorro-maltes-2.jpg",
      "foto2": "https://encrypted-tbn0.gstatic.com/images?q=tbn:ANd9GcTOzRcUtdBdNBt2oyw_5UP37HVZij-qS1qIRw&s",
      "foto3": "https://media.istockphoto.com/id/961585286/pt/foto/maltese-dog-puppy.jpg?s=612x612&w=0&k=20&c=9Aq-sn2SDKXrwQr7qRGcfNAmHIYzmlhd5QoN7DgogYM=",
      "bio": "Daisy é uma Maltês delicada e cheia de amor para dar. Sempre pronta para receber carinho, ela adora estar no colo.",
      "abrigo": "Coração Canino"
    },
    {
      "id": 26,
      "nome": "Ragnar",
      "idade": 5,
      "peso": 28,
      "raca": "Akita Inu",
      "porte": "Grande",
      "foto": "https://upload.wikimedia.org/wikipedia/commons/7/78/Akita_inu.jpeg",
      "foto2": "https://static.wixstatic.com/media/cb07a6_b12ee4bf7ba548ffb4324564a0790ca1~mv2.jpg/v1/fill/w_568,h_550,al_c,q_80,usm_0.66_1.00_0.01,enc_avif,quality_auto/cb07a6_b12ee4bf7ba548ffb4324564a0790ca1~mv2.jpg",
      "foto3": "https://encrypted-tbn0.gstatic.com/images?q=tbn:ANd9GcS35FOlX32gIITjCd93cILAVg8JL2N89rBpVg&s",
      "bio": "Ragnar é um Akita Inu majestoso e leal. Sua personalidade forte e seu carinho pelos donos fazem dele um amigo incrível.",
      "abrigo": "Lar dos Peludos"
    },
    {
      "id": 27,
      "nome": "Chico",
      "idade": 3,
      "peso": 7,
      "raca": "Fox Terrier",
      "porte": "Pequeno",
      "foto": "https://cobasi.vteximg.com.br/arquivos/fox-terrier-de-pelo-duro-meio.png?v=637617197041100000",
      "foto2": "https://encrypted-tbn0.gstatic.com/images?q=tbn:ANd9GcQaj_vz2_x8u5MTOwmE-eCBNFQdUm1RwJnwGg&s",
      "foto3": "https://tudodebicho.vtexassets.com/arquivos/fox-terrier-de-pelo-duro-na-grama.png",
      "bio": "Chico é um Fox Terrier animado e brincalhão. Ele adora desafios e está sempre pronto para novas aventuras.",
      "abrigo": "Lar dos Peludos"
    },
    {
      "id": 28,
      "nome": "Charlotte",
      "idade": 2,
      "peso": 12,
      "raca": "Shar Pei",
      "porte": "Médio",
      "foto": "https://pet-health-content-media.chewy.com/wp-content/uploads/2024/09/11171105/202106GettyImages-1283678952-scaled-1.jpg",
      "foto2": "https://midias.em.com.br/_midias/jpg/2024/09/13/shar_pei-39935830.jpg",
      "foto3": "https://consultadogvet.wordpress.com/wp-content/uploads/2017/02/rac3a7a-27-jayne-the-chinese-shar-pei.jpg?w=616",
      "bio": "Charlotte é uma Shar Pei encantadora e de personalidade marcante. Com seu jeitinho tranquilo, ela conquista qualquer um.",
      "abrigo": "Lar dos Peludos"
    },
    {
      "id": 29,
      "nome": "Floquinho",
      "idade": 6,
      "peso": 20,
      "raca": "Dálmata",
      "porte": "Médio",
      "foto": "https://www.petz.com.br/cachorro/racas/dalmata/img/dalmata-caracteristicas-guia-racas.jpg",
      "foto2": "https://jpimg.com.br/uploads/2023/11/conheca-as-caracteristicas-da-raca-dalmata.jpg",
      "foto3": "https://www.patasdacasa.com.br/sites/default/files/styles/article_detail_1200/public/2024-03/dalmata0.jpg.webp?itok=1Ok0fpoz",
      "bio": "Floquinho é um Dálmata cheio de energia e alegria. Adora correr e brincar, sempre espalhando boas vibrações.",
      "abrigo": "Esperança Animal"
    },
    {
      "id": 30,
      "nome": "Fiona",
      "idade": 4,
      "peso": 30,
      "raca": "Weimaraner",
      "porte": "Grande",
      "foto": "https://cobasi.vteximg.com.br/arquivos/ids/573854/weimaraner-saiba-tudo-sobre-a-raca-meio-3.png?v=637568744215230000",
      "foto2": "https://static.wixstatic.com/media/db516d_cc05ff018abc439e99b461a1143d5668~mv2.jpg/v1/fill/w_640,h_506,al_c,q_80,usm_1.20_1.00_0.01,enc_avif,quality_auto/db516d_cc05ff018abc439e99b461a1143d5668~mv2.jpg",
      "foto3": "https://lh3.googleusercontent.com/proxy/i1itQc_XNvgvc49_p0Nl7oLFZKu-_pAFMuigDvKbyIx37S_4opvRI5OqG_TFF6aF6rXKLH_XRI-bc1ziUqdQBNnpO-Pt7YCurnraFWshOvY6F7wL",
      "bio": "Fiona é uma Weimaraner elegante e inteligente. Com seu olhar expressivo, ela conquista o coração de todos.",
      "abrigo": "Refúgio dos Focinhos"
    }
  ]
}
